siigo_connector/__init__.py
siigo_connector/_http.py
siigo_connector/auth.py
siigo_connector/client.py
siigo_connector/config.py
siigo_connector/errors.py
siigo_connector/resources/customers.py
siigo_connector/resources/products.py
siigo_connector-0.2.7.dist-info/METADATA
siigo_connector-0.2.7.dist-info/WHEEL
siigo_connector-0.2.7.dist-info/licenses/LICENSE
siigo_connector-0.2.7.dist-info/RECORD
