Metadata-Version: 2.4
Name: siigo_connector
Version: 0.2.7
Summary: Python client for the Siigo API
Project-URL: homepage, https://github.com/arendondiosa/siigo-connector-py
Project-URL: repository, https://github.com/arendondiosa/siigo-connector-py
Project-URL: bug, https://github.com/arendondiosa/siigo-connector-py/issues
Project-URL: download, https://github.com/arendondiosa/siigo-connector-py/releases
Project-URL: changelog, https://github.com/arendondiosa/siigo-connector-py/releases
Author-email: "Alejandro E. Rendon" <arendondiosa@gmail.com>
License-Expression: MIT-open-group
License-File: LICENSE
Classifier: License :: OSI Approved :: MIT License
Classifier: Programming Language :: Python :: 3
Classifier: Programming Language :: Python :: 3.9
Classifier: Programming Language :: Python :: 3.10
Classifier: Programming Language :: Python :: 3.11
Classifier: Programming Language :: Python :: 3.12
Requires-Dist: httpx<0.29.0,>=0.28.1
Requires-Dist: pydantic[email]<3.0.0,>=2.11.7
Requires-Dist: tenacity>=9.1.2
